nlubridge/__init__.py
nlubridge/datasets.py
nlubridge/nlu_dataset.py
nlubridge/dataloaders/__init__.py
nlubridge/dataloaders/huggingface.py
nlubridge/dataloaders/luis.py
nlubridge/dataloaders/rasa.py
nlubridge/dataloaders/utils.py
nlubridge/dataloaders/watson_assistant.py
nlubridge/vendors/__init__.py
nlubridge/vendors/char_ngram_intent_classifier.py
nlubridge/vendors/fasttext.py
nlubridge/vendors/luis.py
nlubridge/vendors/rasa2.py
nlubridge/vendors/rasa3.py
nlubridge/vendors/spacy.py
nlubridge/vendors/tfidf_intent_classifier.py
nlubridge/vendors/vendor.py
nlubridge/vendors/watson_assistant.py
nlubridge/vendors/config/rasa_nlu_config.yml
nlubridge-1.0.2.dist-info/LICENSE
nlubridge-1.0.2.dist-info/METADATA
nlubridge-1.0.2.dist-info/WHEEL
nlubridge-1.0.2.dist-info/top_level.txt
nlubridge-1.0.2.dist-info/RECORD
