Metadata-Version: 2.1
Name: nlubridge
Version: 1.0.2
Summary: Provides a unified API to several popular intent recognition applications
Home-page: https://github.com/telekom/nlu-bridge
Author: Klaus-Peter Engelbrecht
Author-email: k.engelbrecht@telekom.de
Maintainer: Klaus-Peter Engelbrecht
Project-URL: Bug Tracker, https://github.com/telekom/nlu-bridge/issues
Project-URL: Source Code, https://github.com/telekom/nlu-bridge
Project-URL: Contributing, https://github.com/telekom/nlu-bridge/blob/main/CONTRIBUTING.md
Project-URL: Code of Conduct, https://github.com/telekom/nlu-bridge/blob/main/CODE_OF_CONDUCT.md
Keywords: nlu,intent recognition,natural language understanding,evaluation,performance
Requires-Python: >=3.8
License-File: LICENSE
Requires-Dist: scikit-learn
Requires-Dist: python-dotenv
Requires-Dist: lazy-imports
Requires-Dist: ratelimit
Provides-Extra: develop
Requires-Dist: pytest-cov ; extra == 'develop'
Requires-Dist: pytest-mock ; extra == 'develop'
Requires-Dist: flake8 ; extra == 'develop'
Requires-Dist: black ; extra == 'develop'
Requires-Dist: pydocstyle ; extra == 'develop'
Requires-Dist: setuptools ; extra == 'develop'
Requires-Dist: wheel ; extra == 'develop'
Requires-Dist: twine ; extra == 'develop'
Requires-Dist: isort ; extra == 'develop'
Requires-Dist: mdformat ; extra == 'develop'
Requires-Dist: mypy ; extra == 'develop'
Requires-Dist: pylint (==2.14.5) ; extra == 'develop'
Provides-Extra: fasttext
Requires-Dist: fasttext ; extra == 'fasttext'
Provides-Extra: huggingface
Requires-Dist: datasets (~=1.18) ; extra == 'huggingface'
Provides-Extra: luis
Requires-Dist: requests ; extra == 'luis'
Requires-Dist: ratelimit ; extra == 'luis'
Provides-Extra: rasa2
Requires-Dist: rasa (~=2.8.0) ; extra == 'rasa2'
Requires-Dist: websockets (~=10.4) ; extra == 'rasa2'
Provides-Extra: rasa3
Requires-Dist: rasa (==3.4.4) ; extra == 'rasa3'
Requires-Dist: websockets (~=10.4) ; extra == 'rasa3'
Provides-Extra: spacy
Requires-Dist: spacy (==3.1.3) ; extra == 'spacy'
Provides-Extra: watson
Requires-Dist: ibm-watson ; extra == 'watson'
Requires-Dist: tqdm ; extra == 'watson'
Requires-Dist: requests ; extra == 'watson'
